swarmauri_typing/Intersection.py
swarmauri_typing/UnionFactory.py
swarmauri_typing/__init__.py
swarmauri_typing-0.7.5.dist-info/METADATA
swarmauri_typing-0.7.5.dist-info/WHEEL
swarmauri_typing-0.7.5.dist-info/RECORD
